niamoto/__init__.py
niamoto/__main__.py
niamoto/__version__.py
niamoto/main.py
niamoto/cli/__init__.py
niamoto/cli/commands/__init__.py
niamoto/cli/commands/base.py
niamoto/cli/commands/deploy.py
niamoto/cli/commands/export.py
niamoto/cli/commands/gui.py
niamoto/cli/commands/imports.py
niamoto/cli/commands/initialize.py
niamoto/cli/commands/optimize.py
niamoto/cli/commands/plugins.py
niamoto/cli/commands/run.py
niamoto/cli/commands/stats.py
niamoto/cli/commands/transform.py
niamoto/cli/utils/__init__.py
niamoto/cli/utils/console.py
niamoto/cli/utils/metrics.py
niamoto/cli/utils/progress.py
niamoto/common/__init__.py
niamoto/common/bundle.py
niamoto/common/config.py
niamoto/common/database.py
niamoto/common/environment.py
niamoto/common/exceptions.py
niamoto/common/paths.py
niamoto/common/progress.py
niamoto/common/resource_paths.py
niamoto/common/utils/__init__.py
niamoto/common/utils/data_access.py
niamoto/common/utils/dict_utils.py
niamoto/common/utils/error_handler.py
niamoto/common/utils/logging_utils.py
niamoto/core/__init__.py
niamoto/core/imports/auto_detector.py
niamoto/core/imports/bootstrap.py
niamoto/core/imports/config_models.py
niamoto/core/imports/engine.py
niamoto/core/imports/hierarchy_builder.py
niamoto/core/imports/ml_detector.py
niamoto/core/imports/profiler.py
niamoto/core/imports/registry.py
niamoto/core/plugins/__init__.py
niamoto/core/plugins/base.py
niamoto/core/plugins/exceptions.py
niamoto/core/plugins/models.py
niamoto/core/plugins/plugin_loader.py
niamoto/core/plugins/registry.py
niamoto/core/plugins/exporters/__init__.py
niamoto/core/plugins/exporters/dwc_archive_exporter.py
niamoto/core/plugins/exporters/html_page_exporter.py
niamoto/core/plugins/exporters/index_generator.py
niamoto/core/plugins/exporters/json_api_exporter.py
niamoto/core/plugins/loaders/__init__.py
niamoto/core/plugins/loaders/adjacency_list.py
niamoto/core/plugins/loaders/api_taxonomy_enricher.py
niamoto/core/plugins/loaders/direct_reference.py
niamoto-0.7.5.dist-info/METADATA
niamoto-0.7.5.dist-info/WHEEL
niamoto-0.7.5.dist-info/entry_points.txt
niamoto-0.7.5.dist-info/licenses/LICENSE
niamoto-0.7.5.dist-info/RECORD
