Metadata-Version: 2.4
Name: niamoto
Version: 0.7.5
Project-URL: Homepage, https://github.com/niamoto/niamoto
Project-URL: Repository, https://github.com/niamoto/niamoto
Project-URL: Documentation, https://github.com/niamoto/niamoto#readme
Author-email: Julien Barbe <julien.barbe@me.com>
License: GPL-3.0-or-later
License-File: LICENSE
Keywords: niamoto
Classifier: Development Status :: 1 - Planning
Classifier: Environment :: Console
Classifier: Intended Audience :: Developers
Classifier: Intended Audience :: Science/Research
Classifier: License :: OSI Approved :: GNU General Public License v3 or later (GPLv3+)
Classifier: Operating System :: OS Independent
Classifier: Programming Language :: Python :: 3
Classifier: Programming Language :: Python :: 3.11
Classifier: Programming Language :: Python :: 3.12
Classifier: Programming Language :: Python :: 3.13
Classifier: Topic :: Scientific/Engineering :: GIS
Classifier: Topic :: Scientific/Engineering :: Information Analysis
Classifier: Topic :: Scientific/Engineering :: Visualization
Classifier: Topic :: Software Development :: Libraries :: Python Modules
Classifier: Topic :: Utilities
Requires-Python: <4,>=3.11
Requires-Dist: click>=8.3.0
Requires-Dist: duckdb-engine>=0.17.0
Requires-Dist: duckdb>=1.4.2
Requires-Dist: fastapi>=0.121.0
Requires-Dist: fiona>=1.9.6
Requires-Dist: geopandas>=1.0.0
Requires-Dist: httpx>=0.25.0
Requires-Dist: jinja2>=3.1.0
Requires-Dist: markdown-it-py<4.0.0,>=3.0.0
Requires-Dist: numpy<3,>=2.2.3
Requires-Dist: pandas>=2.2.1
Requires-Dist: plotly>=6.4.0
Requires-Dist: pyarrow>=22.0.0
Requires-Dist: pydantic>=2.12.0
Requires-Dist: pyproj>=3.7
Requires-Dist: python-multipart>=0.0.6
Requires-Dist: pyyaml>=6.0.3
Requires-Dist: rasterio>=1.3.9
Requires-Dist: requests>=2.32.5
Requires-Dist: rich>=14.2.0
Requires-Dist: scikit-learn>=1.7.2
Requires-Dist: shapely>=2.0.4
Requires-Dist: sqlalchemy[mypy]>=2.0.44
Requires-Dist: topojson>=1.9
Requires-Dist: uvicorn[standard]>=0.38.0
Provides-Extra: dev
Requires-Dist: bump2version>=1.0.1; extra == 'dev'
Requires-Dist: furo>=2023.9.10; extra == 'dev'
Requires-Dist: hypothesis>=6.88.3; extra == 'dev'
Requires-Dist: ipython>=8.17.2; extra == 'dev'
Requires-Dist: mypy>=1.18.0; extra == 'dev'
Requires-Dist: myst-parser>=4.0; extra == 'dev'
Requires-Dist: pandas-stubs>=2.1.1.230928; extra == 'dev'
Requires-Dist: pathspec>=0.11.2; extra == 'dev'
Requires-Dist: pre-commit>=3.5.0; extra == 'dev'
Requires-Dist: pyperclip>=1.8.2; extra == 'dev'
Requires-Dist: pytest-cov>=4.1.0; extra == 'dev'
Requires-Dist: pytest-mock>=3.12.0; extra == 'dev'
Requires-Dist: pytest-stub>=1.1.0; extra == 'dev'
Requires-Dist: pytest>=7.4.3; extra == 'dev'
Requires-Dist: requests-mock>=1.12.1; extra == 'dev'
Requires-Dist: ruff>=0.1.5; extra == 'dev'
Requires-Dist: setuptools>=75.8.0; extra == 'dev'
Requires-Dist: sphinx-markdown-builder>=0.6.6; extra == 'dev'
Requires-Dist: sphinx>=7.2.6; extra == 'dev'
Requires-Dist: sphinxcontrib-napoleon>=0.7; extra == 'dev'
Requires-Dist: types-click>=7.1.8; extra == 'dev'
Requires-Dist: types-pluggy>=1.2.0.2; extra == 'dev'
Requires-Dist: types-pyyaml>=6.0.12.20240311; extra == 'dev'
Requires-Dist: types-shapely>=2.0.0; extra == 'dev'
Requires-Dist: types-tabulate>=0.9.0.3; extra == 'dev'
